gitbolt/__init__.py
gitbolt/_internal_init.py
gitbolt/add.py
gitbolt/base.py
gitbolt/constants.py
gitbolt/exceptions.py
gitbolt/ls_tree.py
gitbolt/models.py
gitbolt/py.typed
gitbolt/pytest_plugin.py
gitbolt/utils.py
gitbolt/subprocess/__init__.py
gitbolt/subprocess/_internal_init.py
gitbolt/subprocess/add.py
gitbolt/subprocess/base.py
gitbolt/subprocess/constants.py
gitbolt/subprocess/exceptions.py
gitbolt/subprocess/ls_tree.py
gitbolt/subprocess/utils.py
gitbolt/subprocess/impl/__init__.py
gitbolt/subprocess/impl/simple.py
gitbolt/subprocess/runner/__init__.py
gitbolt/subprocess/runner/base.py
gitbolt/subprocess/runner/simple.py
gitbolt-0.0.0.dev14.dist-info/licenses/LICENSE
gitbolt-0.0.0.dev14.dist-info/METADATA
gitbolt-0.0.0.dev14.dist-info/WHEEL
gitbolt-0.0.0.dev14.dist-info/entry_points.txt
gitbolt-0.0.0.dev14.dist-info/top_level.txt
gitbolt-0.0.0.dev14.dist-info/RECORD
