Metadata-Version: 2.4
Name: gitbolt
Version: 0.0.0.dev14
Summary: Fast, flexible and type-safe Git commands in Python.
Author-email: Suhas Krishna Srivastava <suhas.srivastava@vaastav.tech>
Maintainer-email: Suhas Krishna Srivastava <suhas.srivastava@vaastav.tech>
License-Expression: Apache-2.0
Project-URL: homepage, https://github.com/Vaastav-Technologies/py-gitbolt
Project-URL: source, https://github.com/Vaastav-Technologies/py-gitbolt
Project-URL: issues, https://github.com/Vaastav-Technologies/py-gitbolt/issues
Keywords: git,vcs,library,version control
Classifier: Development Status :: 1 - Planning
Classifier: Intended Audience :: Developers
Classifier: Intended Audience :: Education
Classifier: Topic :: Education
Classifier: Topic :: Software Development
Classifier: Topic :: Software Development :: Libraries
Classifier: Topic :: Software Development :: Libraries :: Python Modules
Classifier: Topic :: Software Development :: Version Control
Classifier: Topic :: Software Development :: Version Control :: Git
Classifier: Operating System :: OS Independent
Classifier: Programming Language :: Python :: 3.12
Classifier: Programming Language :: Python :: 3.13
Classifier: Programming Language :: Python :: 3 :: Only
Classifier: Typing :: Typed
Requires-Python: >=3.12
License-File: LICENSE
Requires-Dist: vt-err-hndlr>=0.0.0dev6
Requires-Dist: vt-commons>=0.0.1.dev9
Provides-Extra: pygit2
Requires-Dist: pygit2; extra == "pygit2"
Provides-Extra: test
Requires-Dist: pytest; extra == "test"
Dynamic: license-file
